hankai/__init__.py
hankai/autocoding/__init__.py
hankai/autocoding/bin/__init__.py
hankai/autocoding/bin/liaison.py
hankai/autocoding/bin/scaling_manager_ecs_by_sqs.py
hankai/autocoding/lib/__init__.py
hankai/autocoding/lib/enum_other.py
hankai/autocoding/lib/liaison.py
hankai/autocoding/lib/liaison_set_1_processor.py
hankai/autocoding/lib/no_core_models.py
hankai/autocoding/lib/sqs.py
hankai/autocoding/lib/sqs_request.py
hankai/autocoding/lib/sqs_response.py
hank_ai_autocoding-3.2.3.dist-info/METADATA
hank_ai_autocoding-3.2.3.dist-info/WHEEL
hank_ai_autocoding-3.2.3.dist-info/entry_points.txt
hank_ai_autocoding-3.2.3.dist-info/namespace_packages.txt
hank_ai_autocoding-3.2.3.dist-info/top_level.txt
hank_ai_autocoding-3.2.3.dist-info/RECORD
