Metadata-Version: 2.1
Name: hank-ai-autocoding
Version: 3.2.3
Summary: Hank AI AutoCoding for Hank AI projects.
Home-page: https://github.com/hank-ai/mondo/tree/main/src/python/hank-ai-autocoding
Download-URL: https://pypi.org/project/hank-ai-autocoding/
Author: Hank AI, Inc.
Author-email: sysadmin@hank.ai
License: MIT
Platform: any
Classifier: Development Status :: 5 - Production/Stable
Classifier: Environment :: Other Environment
Classifier: Intended Audience :: Developers
Classifier: License :: OSI Approved :: MIT License
Classifier: Natural Language :: English
Classifier: Operating System :: OS Independent
Classifier: Programming Language :: Python :: 3 :: Only
Classifier: Programming Language :: Python :: 3.8
Classifier: Programming Language :: Python :: 3.9
Classifier: Programming Language :: Python :: 3.10
Classifier: Programming Language :: Python :: Implementation :: CPython
Classifier: Topic :: Software Development :: Libraries :: Python Modules
Classifier: Typing :: Typed
Requires-Python: <3.11,>=3.8
Requires-Dist: hank-ai-aws (~=3.2.3)
Requires-Dist: hank-ai-lib (~=3.2.3)
Requires-Dist: hank-ai-orchestrator (~=3.2.3)
Requires-Dist: backoff (~=2.2.1) ; python_version >= "3.8" and python_version < "3.11"
Requires-Dist: jsonpickle (~=3.0.1) ; python_version >= "3.8" and python_version < "3.11"
